satang_pro_signer/__init__.py
satang_pro_signer/preparer.py
satang_pro_signer/signer.py
signer/__init__.py
signer/preparer.py
signer/signer.py
satang_pro_signer_x-0.0.1.dev2.dist-info/LICENSE
satang_pro_signer_x-0.0.1.dev2.dist-info/METADATA
satang_pro_signer_x-0.0.1.dev2.dist-info/WHEEL
satang_pro_signer_x-0.0.1.dev2.dist-info/top_level.txt
satang_pro_signer_x-0.0.1.dev2.dist-info/RECORD
