Metadata-Version: 2.1
Name: satang-pro-signer-x
Version: 0.0.1.dev2
Summary: An implementation of Satang Pro signing request scheme
Home-page: https://github.com/thebevrishot/satang-pro-signer
Author: Panu
Author-email: Panu.suk@protonmail.com
License: UNKNOWN
Platform: UNKNOWN
Classifier: Programming Language :: Python :: 3
Classifier: License :: OSI Approved :: MIT License
Classifier: Operating System :: OS Independent
Requires-Python: >=3.6
